iiris_elasticsearch/__init__.py
iiris_elasticsearch/elasticsearch.py
roop_elasticsearch/__init__.py
roop_elasticsearch/elasticsearch.py
iiris_elasticsearch-0.0.3.dist-info/METADATA
iiris_elasticsearch-0.0.3.dist-info/WHEEL
iiris_elasticsearch-0.0.3.dist-info/top_level.txt
iiris_elasticsearch-0.0.3.dist-info/RECORD
